setup.py
stq.py
simpletq.egg-info/PKG-INFO
simpletq.egg-info/SOURCES.txt
simpletq.egg-info/dependency_links.txt
simpletq.egg-info/top_level.txt