Metadata-Version: 1.1
Name: simpletq
Version: 0.1.dev1
Summary: A very simple task queue
Home-page: https://github.com/sdrave/simpletq
Author: Stephan Rave
Author-email: mail@stephanrave.de
License: BSD License
Keywords: simulation data numerics reproducibility
Platform: UNKNOWN
Classifier: Development Status :: 3 - Alpha
Classifier: Intended Audience :: Developers
Classifier: Intended Audience :: End Users/Desktop
Classifier: Intended Audience :: Other Audience
Classifier: Intended Audience :: Science/Research
Classifier: Intended Audience :: System Administrators
Classifier: License :: OSI Approved :: BSD License
Classifier: Programming Language :: Python :: 2
Classifier: Programming Language :: Python :: 2.7
Classifier: Topic :: Scientific/Engineering
Classifier: Topic :: System :: Distributed Computing
Classifier: Topic :: Utilities
